RainbowMonitoringSDK/__init__.py
RainbowMonitoringSDK/controller.py
RainbowMonitoringSDK/exporters/Exporter.py
RainbowMonitoringSDK/exporters/__init__.py
RainbowMonitoringSDK/exporters/exporterlib/APIcallExporter.py
RainbowMonitoringSDK/exporters/exporterlib/IgniteExporter.py
RainbowMonitoringSDK/exporters/exporterlib/KafkaExporter.py
RainbowMonitoringSDK/exporters/exporterlib/MockExporter.py
RainbowMonitoringSDK/exporters/exporterlib/RestAPIExporter.py
RainbowMonitoringSDK/exporters/exporterlib/__init__.py
RainbowMonitoringSDK/probes/Metric.py
RainbowMonitoringSDK/probes/Probe.py
RainbowMonitoringSDK/probes/__init__.py
RainbowMonitoringSDK/probes/utils.py
RainbowMonitoringSDK/probes/probelib/AppMetricsProbe.py
RainbowMonitoringSDK/probes/probelib/DockerProbe.py
RainbowMonitoringSDK/probes/probelib/NetDataProbe.py
RainbowMonitoringSDK/probes/probelib/ServerAppMetricsProbe.py
RainbowMonitoringSDK/probes/probelib/WebAppMetricsProbe.py
RainbowMonitoringSDK/probes/probelib/__init__.py
RainbowMonitoringSDK/samplers/Datapoint.py
RainbowMonitoringSDK/samplers/Sample.py
RainbowMonitoringSDK/samplers/__init__.py
RainbowMonitoringSDK/samplers/adam/__init__.py
RainbowMonitoringSDK/samplers/adam/estimators/PEWMA.py
RainbowMonitoringSDK/samplers/adam/estimators/__init__.py
RainbowMonitoringSDK/samplers/adam/main/AdaM.py
RainbowMonitoringSDK/samplers/adam/main/__init__.py
RainbowMonitoringSDK/samplers/admin/__init__.py
RainbowMonitoringSDK/samplers/admin/change_detectors/OnlineCUSUMv2.py
RainbowMonitoringSDK/samplers/admin/change_detectors/__init__.py
RainbowMonitoringSDK/samplers/admin/estimators/HoltWintersSeasonalwithPEWMA.py
RainbowMonitoringSDK/samplers/admin/estimators/HoltsLinearSophisticTrendwithPEWMA.py
RainbowMonitoringSDK/samplers/admin/estimators/__init__.py
RainbowMonitoringSDK/samplers/admin/main/ADMinNoSeasonal.py
RainbowMonitoringSDK/samplers/admin/main/__init__.py
RainbowMonitoringSDK/tests/__init__.py
RainbowMonitoringSDK/tests/test_AppMetricsProbe.py
RainbowMonitoringSDK-0.0.7.dist-info/LICENSE.txt
RainbowMonitoringSDK-0.0.7.dist-info/METADATA
RainbowMonitoringSDK-0.0.7.dist-info/WHEEL
RainbowMonitoringSDK-0.0.7.dist-info/top_level.txt
RainbowMonitoringSDK-0.0.7.dist-info/RECORD
