Metadata-Version: 2.1
Name: RainbowMonitoringSDK
Version: 0.0.7
Summary: The Rainbow's Monitoring SDK library
Author: Moysis Symeonides, Joanna Georgiou
Author-email: symeonidis.moysis@cs.ucy.ac.cy, georgiou.joanna@cs.ucy.ac.cy
Requires-Python: >=3.5
License-File: LICENSE.txt
Requires-Dist: requests
Requires-Dist: pyyaml
Requires-Dist: Flask
Requires-Dist: kafka
Requires-Dist: ConfigUpdater
Requires-Dist: docker
